odoo/addons/sale_report_delivered_brand/README.rst
odoo/addons/sale_report_delivered_brand/__init__.py
odoo/addons/sale_report_delivered_brand/__manifest__.py
odoo/addons/sale_report_delivered_brand/i18n/es.po
odoo/addons/sale_report_delivered_brand/i18n/sale_report_delivered_brand.pot
odoo/addons/sale_report_delivered_brand/models/__init__.py
odoo/addons/sale_report_delivered_brand/models/sale_report_delivered.py
odoo/addons/sale_report_delivered_brand/readme/CONTRIBUTORS.md
odoo/addons/sale_report_delivered_brand/readme/DESCRIPTION.md
odoo/addons/sale_report_delivered_brand/readme/USAGE.md
odoo/addons/sale_report_delivered_brand/static/description/icon.png
odoo/addons/sale_report_delivered_brand/static/description/index.html
odoo/addons/sale_report_delivered_brand/tests/__init__.py
odoo/addons/sale_report_delivered_brand/tests/test_sale_report_delivered_brand.py
odoo/addons/sale_report_delivered_brand/views/sale_report_delivered_views.xml
odoo_addon_sale_report_delivered_brand-18.0.1.0.1.2.dist-info/METADATA
odoo_addon_sale_report_delivered_brand-18.0.1.0.1.2.dist-info/WHEEL
odoo_addon_sale_report_delivered_brand-18.0.1.0.1.2.dist-info/top_level.txt
odoo_addon_sale_report_delivered_brand-18.0.1.0.1.2.dist-info/RECORD
