Metadata-Version: 2.1
Name: odoo-addon-sale_report_delivered_brand
Version: 18.0.1.0.1.2
Requires-Python: >=3.10
Requires-Dist: odoo-addon-product_brand==18.0.*
Requires-Dist: odoo-addon-sale_report_delivered==18.0.*
Requires-Dist: odoo==18.0.*
Summary: Sale Report Delivered Brand
Home-page: https://github.com/OCA/sale-reporting
License: AGPL-3
Author: Tecnativa, Odoo Community Association (OCA)
Author-email: support@odoo-community.org
Classifier: Programming Language :: Python
Classifier: Framework :: Odoo
Classifier: Framework :: Odoo :: 18.0
Classifier: License :: OSI Approved :: GNU Affero General Public License v3
